abcvlib/__init__.py
abcvlib/server.py
abcvlib/setup_config.py
abcvlib-0.0.7.dist-info/METADATA
abcvlib-0.0.7.dist-info/WHEEL
abcvlib-0.0.7.dist-info/RECORD
